config/__init__.py
config/config.py
config/py.typed
config/trace.py
pythonic_config-0.7.0.dist-info/LICENSE
pythonic_config-0.7.0.dist-info/METADATA
pythonic_config-0.7.0.dist-info/WHEEL
pythonic_config-0.7.0.dist-info/top_level.txt
pythonic_config-0.7.0.dist-info/zip-safe
pythonic_config-0.7.0.dist-info/RECORD
